{
  "generatedAt": "2026-03-01T21:37:30.130Z",
  "generatedAtIOS": "Mar 1, 2026 at 1:37 PM",
  "itemCount": 6,
  "items": [
    {
      "title": "JD OS Cloudflare Ideas",
      "sourceType": "transcript",
      "sourceId": "10397359-edc5-4dd3-8570-0ec5514490df",
      "timestampSortable": "2026-03-01-20-46-56",
      "timestampIOS": "Mar 1, 2026 at 12:46 PM",
      "href": "/how-this-is-built/logs/2026-03-01-20-46-56_jd-os-cloudflare-ideas.md"
    },
    {
      "title": "Webflow Site Duplication Plan",
      "sourceType": "plan",
      "sourceId": "webflow_site_duplication_4a1135b8.plan",
      "timestampSortable": "2026-03-01-20-57-06",
      "timestampIOS": "Mar 1, 2026 at 12:57 PM",
      "href": "/how-this-is-built/logs/2026-03-01-20-57-06_webflow-site-duplication-plan.md"
    },
    {
      "title": "Webflow Clone Build Log",
      "sourceType": "transcript",
      "sourceId": "2d266c2e-67e2-469d-a82d-fef6973a8c55",
      "timestampSortable": "2026-03-01-21-27-38",
      "timestampIOS": "Mar 1, 2026 at 1:27 PM",
      "href": "/how-this-is-built/logs/2026-03-01-21-27-38_webflow-clone-build-log.md"
    },
    {
      "title": "update origin, it's pointed to the...",
      "sourceType": "transcript",
      "sourceId": "eb5305a5-2005-4f5d-9639-61f41d60be47",
      "timestampSortable": "2026-03-01-21-29-00",
      "timestampIOS": "Mar 1, 2026 at 1:29 PM",
      "href": "/how-this-is-built/logs/2026-03-01-21-29-00_update-origin-it-s-pointed-to-the.md"
    },
    {
      "title": "update this README.md to be a...",
      "sourceType": "transcript",
      "sourceId": "5bf8bfb4-f841-42c1-bd73-4075efcf510b",
      "timestampSortable": "2026-03-01-21-36-51",
      "timestampIOS": "Mar 1, 2026 at 1:36 PM",
      "href": "/how-this-is-built/logs/2026-03-01-21-36-51_update-this-readme-md-to-be-a.md"
    },
    {
      "title": "tags. 2. **Tool calls**: Tool calls...",
      "sourceType": "transcript",
      "sourceId": "23e1d4d7-e02d-40a0-8264-02bdb4e7e620",
      "timestampSortable": "2026-03-01-21-37-30",
      "timestampIOS": "Mar 1, 2026 at 1:37 PM",
      "href": "/how-this-is-built/logs/2026-03-01-21-37-30_tags-2-tool-calls-tool-calls.md"
    }
  ]
}
